constructional_complexity_analyzer/__init__.py
constructional_complexity_analyzer/__main__.py
constructional_complexity_analyzer/cli.py
constructional_complexity_analyzer/core.py
constructional_complexity_analyzer/utils.py
constructional_complexity_analyzer-0.3.0.dist-info/METADATA
constructional_complexity_analyzer-0.3.0.dist-info/WHEEL
constructional_complexity_analyzer-0.3.0.dist-info/entry_points.txt
constructional_complexity_analyzer-0.3.0.dist-info/top_level.txt
constructional_complexity_analyzer-0.3.0.dist-info/RECORD
